odoo/addons/sale_packaging_report/README.rst
odoo/addons/sale_packaging_report/__init__.py
odoo/addons/sale_packaging_report/__manifest__.py
odoo/addons/sale_packaging_report/i18n/es.po
odoo/addons/sale_packaging_report/i18n/it.po
odoo/addons/sale_packaging_report/i18n/sale_packaging_report.pot
odoo/addons/sale_packaging_report/readme/CONFIGURE.md
odoo/addons/sale_packaging_report/readme/CONTRIBUTORS.md
odoo/addons/sale_packaging_report/readme/DESCRIPTION.md
odoo/addons/sale_packaging_report/readme/USAGE.md
odoo/addons/sale_packaging_report/report/__init__.py
odoo/addons/sale_packaging_report/report/sale_report.py
odoo/addons/sale_packaging_report/report/sale_report_view.xml
odoo/addons/sale_packaging_report/static/description/icon.png
odoo/addons/sale_packaging_report/static/description/index.html
odoo/addons/sale_packaging_report/tests/__init__.py
odoo/addons/sale_packaging_report/tests/test_sale_packaging_report.py
odoo/addons/sale_packaging_report/views/report_sale_order.xml
odoo_addon_sale_packaging_report-18.0.1.0.0.2.dist-info/METADATA
odoo_addon_sale_packaging_report-18.0.1.0.0.2.dist-info/WHEEL
odoo_addon_sale_packaging_report-18.0.1.0.0.2.dist-info/top_level.txt
odoo_addon_sale_packaging_report-18.0.1.0.0.2.dist-info/RECORD
